statefun_tasks/__init__.py
statefun_tasks/builtin.py
statefun_tasks/builtin_tasks.py
statefun_tasks/default_serialiser.py
statefun_tasks/flink_task.py
statefun_tasks/flink_tasks.py
statefun_tasks/messages_pb2.py
statefun_tasks/pipeline_builder.py
statefun_tasks/protobuf.py
statefun_tasks/task_context.py
statefun_tasks/type_helpers.py
statefun_tasks/types.py
statefun_tasks/utils.py
statefun_tasks/client/__init__.py
statefun_tasks/client/tasks_client.py
statefun_tasks/client/types.py
statefun_tasks/core/__init__.py
statefun_tasks/core/statefun/__init__.py
statefun_tasks/core/statefun/context.py
statefun_tasks/core/statefun/core.py
statefun_tasks/core/statefun/egress_io.py
statefun_tasks/core/statefun/kafka_egress_pb2.py
statefun_tasks/core/statefun/kinesis_egress_pb2.py
statefun_tasks/core/statefun/messages.py
statefun_tasks/core/statefun/request_reply_pb2.py
statefun_tasks/core/statefun/request_reply_v3.py
statefun_tasks/core/statefun/statefun_builder.py
statefun_tasks/core/statefun/storage.py
statefun_tasks/core/statefun/types_pb2.py
statefun_tasks/core/statefun/utils.py
statefun_tasks/core/statefun/wrapper_types.py
statefun_tasks/effects/__init__.py
statefun_tasks/effects/effect.py
statefun_tasks/effects/pause_pipeline_effect.py
statefun_tasks/events/__init__.py
statefun_tasks/events/event_handlers.py
statefun_tasks/extensions/__init__.py
statefun_tasks/extensions/inline_tasks/__init__.py
statefun_tasks/extensions/inline_tasks/inline_tasks_impl.py
statefun_tasks/handlers/__init__.py
statefun_tasks/handlers/message_handler.py
statefun_tasks/handlers/task_action_handler.py
statefun_tasks/handlers/task_request_handler.py
statefun_tasks-1.2.4.dist-info/licenses/LICENSE
statefun_tasks-1.2.4.dist-info/METADATA
statefun_tasks-1.2.4.dist-info/WHEEL
statefun_tasks-1.2.4.dist-info/top_level.txt
statefun_tasks-1.2.4.dist-info/RECORD
