Metadata-Version: 2.4
Name: statefun-tasks
Version: 1.2.4
Summary: Tasks API for Stateful Functions on Flink
Home-page: https://fransking.github.io/flink-statefun-tasks
Author: Frans King & Luke Ashworth
Author-email: frans.king@sbbsystems.com
License: https://www.apache.org/licenses/LICENSE-2.0
Classifier: License :: OSI Approved :: Apache Software License
Classifier: Programming Language :: Python :: 3.10
Classifier: Programming Language :: Python :: 3.11
Classifier: Programming Language :: Python :: 3.12
Requires-Python: >=3.10
License-File: LICENSE
Requires-Dist: kafka-python
Requires-Dist: protobuf
Dynamic: author
Dynamic: author-email
Dynamic: classifier
Dynamic: description
Dynamic: description-content-type
Dynamic: home-page
Dynamic: license
Dynamic: license-file
Dynamic: requires-dist
Dynamic: requires-python
Dynamic: summary
